{
  "formatVersion": 1,
  "database": {
    "version": 2,
    "identityHash": "c1f80fc4f21f1c975cba0efcf962a724",
    "entities": [
      {
        "tableName": "scores",
        "createSql": "CREATE TABLE IF NOT EXISTS `${TABLE_NAME}` (`id` INTEGER PRIMARY KEY AUTOINCREMENT NOT NULL, `title` TEXT NOT NULL, `filePath` TEXT NOT NULL, `createdAt` INTEGER NOT NULL, `updatedAt` INTEGER NOT NULL, `rating` INTEGER, `difficulty` INTEGER, `duration` INTEGER, `keySignature` TEXT, `timeSignature` TEXT, `composerId` INTEGER, FOREIGN KEY(`composerId`) REFERENCES `composers`(`id`) ON UPDATE NO ACTION ON DELETE SET NULL )",
        "fields": [
          {
            "fieldPath": "id",
            "columnName": "id",
            "affinity": "INTEGER",
            "notNull": true
          },
          {
            "fieldPath": "title",
            "columnName": "title",
            "affinity": "TEXT",
            "notNull": true
          },
          {
            "fieldPath": "filePath",
            "columnName": "filePath",
            "affinity": "TEXT",
            "notNull": true
          },
          {
            "fieldPath": "createdAt",
            "columnName": "createdAt",
            "affinity": "INTEGER",
            "notNull": true
          },
          {
            "fieldPath": "updatedAt",
            "columnName": "updatedAt",
            "affinity": "INTEGER",
            "notNull": true
          },
          {
            "fieldPath": "rating",
            "columnName": "rating",
            "affinity": "INTEGER"
          },
          {
            "fieldPath": "difficulty",
            "columnName": "difficulty",
            "affinity": "INTEGER"
          },
          {
            "fieldPath": "duration",
            "columnName": "duration",
            "affinity": "INTEGER"
          },
          {
            "fieldPath": "keySignature",
            "columnName": "keySignature",
            "affinity": "TEXT"
          },
          {
            "fieldPath": "timeSignature",
            "columnName": "timeSignature",
            "affinity": "TEXT"
          },
          {
            "fieldPath": "composerId",
            "columnName": "composerId",
            "affinity": "INTEGER"
          }
        ],
        "primaryKey": {
          "autoGenerate": true,
          "columnNames": [
            "id"
          ]
        },
        "indices": [
          {
            "name": "index_scores_composerId",
            "unique": false,
            "columnNames": [
              "composerId"
            ],
            "orders": [],
            "createSql": "CREATE INDEX IF NOT EXISTS `index_scores_composerId` ON `${TABLE_NAME}` (`composerId`)"
          }
        ],
        "foreignKeys": [
          {
            "table": "composers",
            "onDelete": "SET NULL",
            "onUpdate": "NO ACTION",
            "columns": [
              "composerId"
            ],
            "referencedColumns": [
              "id"
            ]
          }
        ]
      },
      {
        "tableName": "composers",
        "createSql": "CREATE TABLE IF NOT EXISTS `${TABLE_NAME}` (`id` INTEGER PRIMARY KEY AUTOINCREMENT NOT NULL, `firstName` TEXT, `lastName` TEXT NOT NULL, `createdAt` INTEGER NOT NULL, `updatedAt` INTEGER NOT NULL)",
        "fields": [
          {
            "fieldPath": "id",
            "columnName": "id",
            "affinity": "INTEGER",
            "notNull": true
          },
          {
            "fieldPath": "firstName",
            "columnName": "firstName",
            "affinity": "TEXT"
          },
          {
            "fieldPath": "lastName",
            "columnName": "lastName",
            "affinity": "TEXT",
            "notNull": true
          },
          {
            "fieldPath": "createdAt",
            "columnName": "createdAt",
            "affinity": "INTEGER",
            "notNull": true
          },
          {
            "fieldPath": "updatedAt",
            "columnName": "updatedAt",
            "affinity": "INTEGER",
            "notNull": true
          }
        ],
        "primaryKey": {
          "autoGenerate": true,
          "columnNames": [
            "id"
          ]
        }
      },
      {
        "tableName": "genres",
        "createSql": "CREATE TABLE IF NOT EXISTS `${TABLE_NAME}` (`id` INTEGER PRIMARY KEY AUTOINCREMENT NOT NULL, `name` TEXT NOT NULL)",
        "fields": [
          {
            "fieldPath": "id",
            "columnName": "id",
            "affinity": "INTEGER",
            "notNull": true
          },
          {
            "fieldPath": "name",
            "columnName": "name",
            "affinity": "TEXT",
            "notNull": true
          }
        ],
        "primaryKey": {
          "autoGenerate": true,
          "columnNames": [
            "id"
          ]
        }
      },
      {
        "tableName": "instruments",
        "createSql": "CREATE TABLE IF NOT EXISTS `${TABLE_NAME}` (`id` INTEGER PRIMARY KEY AUTOINCREMENT NOT NULL, `name` TEXT NOT NULL)",
        "fields": [
          {
            "fieldPath": "id",
            "columnName": "id",
            "affinity": "INTEGER",
            "notNull": true
          },
          {
            "fieldPath": "name",
            "columnName": "name",
            "affinity": "TEXT",
            "notNull": true
          }
        ],
        "primaryKey": {
          "autoGenerate": true,
          "columnNames": [
            "id"
          ]
        }
      },
      {
        "tableName": "score_genre_cross_ref",
        "createSql": "CREATE TABLE IF NOT EXISTS `${TABLE_NAME}` (`scoreId` INTEGER NOT NULL, `genreId` INTEGER NOT NULL, PRIMARY KEY(`scoreId`, `genreId`), FOREIGN KEY(`scoreId`) REFERENCES `scores`(`id`) ON UPDATE NO ACTION ON DELETE CASCADE , FOREIGN KEY(`genreId`) REFERENCES `genres`(`id`) ON UPDATE NO ACTION ON DELETE CASCADE )",
        "fields": [
          {
            "fieldPath": "scoreId",
            "columnName": "scoreId",
            "affinity": "INTEGER",
            "notNull": true
          },
          {
            "fieldPath": "genreId",
            "columnName": "genreId",
            "affinity": "INTEGER",
            "notNull": true
          }
        ],
        "primaryKey": {
          "autoGenerate": false,
          "columnNames": [
            "scoreId",
            "genreId"
          ]
        },
        "indices": [
          {
            "name": "index_score_genre_cross_ref_genreId",
            "unique": false,
            "columnNames": [
              "genreId"
            ],
            "orders": [],
            "createSql": "CREATE INDEX IF NOT EXISTS `index_score_genre_cross_ref_genreId` ON `${TABLE_NAME}` (`genreId`)"
          }
        ],
        "foreignKeys": [
          {
            "table": "scores",
            "onDelete": "CASCADE",
            "onUpdate": "NO ACTION",
            "columns": [
              "scoreId"
            ],
            "referencedColumns": [
              "id"
            ]
          },
          {
            "table": "genres",
            "onDelete": "CASCADE",
            "onUpdate": "NO ACTION",
            "columns": [
              "genreId"
            ],
            "referencedColumns": [
              "id"
            ]
          }
        ]
      },
      {
        "tableName": "score_instrument_cross_ref",
        "createSql": "CREATE TABLE IF NOT EXISTS `${TABLE_NAME}` (`scoreId` INTEGER NOT NULL, `instrumentId` INTEGER NOT NULL, PRIMARY KEY(`scoreId`, `instrumentId`), FOREIGN KEY(`scoreId`) REFERENCES `scores`(`id`) ON UPDATE NO ACTION ON DELETE CASCADE , FOREIGN KEY(`instrumentId`) REFERENCES `instruments`(`id`) ON UPDATE NO ACTION ON DELETE CASCADE )",
        "fields": [
          {
            "fieldPath": "scoreId",
            "columnName": "scoreId",
            "affinity": "INTEGER",
            "notNull": true
          },
          {
            "fieldPath": "instrumentId",
            "columnName": "instrumentId",
            "affinity": "INTEGER",
            "notNull": true
          }
        ],
        "primaryKey": {
          "autoGenerate": false,
          "columnNames": [
            "scoreId",
            "instrumentId"
          ]
        },
        "indices": [
          {
            "name": "index_score_instrument_cross_ref_instrumentId",
            "unique": false,
            "columnNames": [
              "instrumentId"
            ],
            "orders": [],
            "createSql": "CREATE INDEX IF NOT EXISTS `index_score_instrument_cross_ref_instrumentId` ON `${TABLE_NAME}` (`instrumentId`)"
          }
        ],
        "foreignKeys": [
          {
            "table": "scores",
            "onDelete": "CASCADE",
            "onUpdate": "NO ACTION",
            "columns": [
              "scoreId"
            ],
            "referencedColumns": [
              "id"
            ]
          },
          {
            "table": "instruments",
            "onDelete": "CASCADE",
            "onUpdate": "NO ACTION",
            "columns": [
              "instrumentId"
            ],
            "referencedColumns": [
              "id"
            ]
          }
        ]
      }
    ],
    "setupQueries": [
      "CREATE TABLE IF NOT EXISTS room_master_table (id INTEGER PRIMARY KEY,identity_hash TEXT)",
      "INSERT OR REPLACE INTO room_master_table (id,identity_hash) VALUES(42, 'c1f80fc4f21f1c975cba0efcf962a724')"
    ]
  }
}